sparc_flow/__init__.py
sparc_flow/core/__init__.py
sparc_flow/core/workflow.py
sparc_flow/utils/__init__.py
sparc_flow/utils/import_code_to_sds.py
sparc_flow-1.0.3.dist-info/LICENSE
sparc_flow-1.0.3.dist-info/METADATA
sparc_flow-1.0.3.dist-info/WHEEL
sparc_flow-1.0.3.dist-info/top_level.txt
sparc_flow-1.0.3.dist-info/RECORD
